LICENSE
MANIFEST.in
README.md
setup.py
covmatic_localwebserver.egg-info/PKG-INFO
covmatic_localwebserver.egg-info/SOURCES.txt
covmatic_localwebserver.egg-info/dependency_links.txt
covmatic_localwebserver.egg-info/requires.txt
covmatic_localwebserver.egg-info/top_level.txt
covmatic_lws/__init__.py
covmatic_lws/api.py
covmatic_lws/args.py
covmatic_lws/check_update.py
covmatic_lws/localwebserver.py
covmatic_lws/protocol_gen.py
covmatic_lws/setup.py
covmatic_lws/ssh.py
covmatic_lws/task_runner.py
covmatic_lws/utils.py
covmatic_lws/gui/__init__.py
covmatic_lws/gui/__main__.py
covmatic_lws/gui/app_buttons.py
covmatic_lws/gui/button_frames.py
covmatic_lws/gui/buttons.py
covmatic_lws/gui/gui.py
covmatic_lws/gui/images.py
covmatic_lws/gui/log.py
covmatic_lws/gui/robot_buttons.py
covmatic_lws/gui/server.py
covmatic_lws/gui/system_version.py
covmatic_lws/gui/tempdeck.py
covmatic_lws/gui/upload_protocol.py
covmatic_lws/gui/utils.py
covmatic_lws/templates/Covmatic_Icon.ico
covmatic_lws/templates/Covmatic_Icon.png
covmatic_lws/templates/Covmatic_Icon_Red.ico
covmatic_lws/templates/Covmatic_Icon_Red.png
covmatic_lws/templates/Covmatic_Logo.png
covmatic_lws/templates/covmatic.desktop
covmatic_lws/templates/covmatic_tempdeck.desktop
covmatic_lws/templates/protocol.py