Metadata-Version: 2.1
Name: covmatic-localwebserver
Version: 2.10.0
Summary: Package for the COVMATIC LocalWebServer
Home-page: https://github.com/covmatic/localwebserver
Author: Marco Tiraboschi
Author-email: marco.tiraboschi@unimi.it
Maintainer: Marco Tiraboschi, Fedrico Insero, Wassim Lababidi
Maintainer-email: marco.tiraboschi@unimi.it, federico.insero@mail.polimi.it, wassim.lababidi@mail.polimi.it
License: UNKNOWN
Platform: UNKNOWN
Classifier: Programming Language :: Python :: 3
Classifier: License :: OSI Approved :: MIT License
Classifier: Operating System :: OS Independent
Requires-Python: >=3.7, <3.9
License-File: LICENSE
